pyalfe/__init__.py
pyalfe/config.ini
pyalfe/containers.py
pyalfe/data_structure.py
pyalfe/image_processing.py
pyalfe/image_registration.py
pyalfe/inference.py
pyalfe/main.py
pyalfe/pipeline.py
pyalfe/roi.py
pyalfe/interfaces/__init__.py
pyalfe/interfaces/c3d.py
pyalfe/interfaces/freesurfer.py
pyalfe/interfaces/greedy.py
pyalfe/models/__init__.py
pyalfe/tasks/__init__.py
pyalfe/tasks/dicom_processing.py
pyalfe/tasks/initialization.py
pyalfe/tasks/quantification.py
pyalfe/tasks/registration.py
pyalfe/tasks/segmentation.py
pyalfe/tasks/skullstripping.py
pyalfe/tasks/t1_postprocessing.py
pyalfe/tasks/t1_preprocessing.py
pyalfe/templates/oasis/T_template0.nii.gz
pyalfe/templates/oasis/T_template0_BrainCerebellum.nii.gz
pyalfe/templates/oasis/T_template0_BrainCerebellumMask.nii.gz
pyalfe/templates/oasis/T_template0_CorpusCallosum.nii.gz
pyalfe/templates/oasis/T_template0_Lobes.nii.gz
pyalfe/templates/oasis/T_template0_Tissue.nii.gz
pyalfe/tools/__init__.py
pyalfe/utils/__init__.py
pyalfe/utils/archive.py
pyalfe/utils/dicom.py
pyalfe/utils/download.py
pyalfe/utils/technique.py
pyalfe-0.1.1.dist-info/LICENSE
pyalfe-0.1.1.dist-info/METADATA
pyalfe-0.1.1.dist-info/WHEEL
pyalfe-0.1.1.dist-info/entry_points.txt
pyalfe-0.1.1.dist-info/top_level.txt
pyalfe-0.1.1.dist-info/RECORD
