Metadata-Version: 2.1
Name: pyalfe
Version: 0.1.1
Summary: A pipeline for Automated Lesion and Feature Extraction from brain MRIs
Author-email: Reza Eghbali <eghbali68@gmail.com>, reza.eghbali@ucsf.edu
License: Copyright 2022 Reza Eghbali
License-File: LICENSE
Requires-Dist: scipy
Requires-Dist: StrEnum
Requires-Dist: numpy
Requires-Dist: Click
Requires-Dist: pydcm2niix
Requires-Dist: huggingface-hub
Requires-Dist: torch
Requires-Dist: pandas
Requires-Dist: picsl-c3d
Requires-Dist: picsl-greedy
Requires-Dist: pybids
Requires-Dist: nibabel
Requires-Dist: nilearn
Requires-Dist: matplotlib
Requires-Dist: nnunet
Requires-Dist: nnunetv2
Provides-Extra: ants
Requires-Dist: antspyx ; extra == 'ants'
Provides-Extra: docs
Requires-Dist: jupyter-book ; extra == 'docs'
Requires-Dist: sphinx-click ; extra == 'docs'
Provides-Extra: radiomics
Requires-Dist: Pyradiomics ; extra == 'radiomics'
